{
 "result": [
  {
   "Id": 34,
   "Score": 0.15265625000000002,
   "Title": "Securing the Smart Devices | HKUST CSE",
   "Url": "https://www.cse.ust.hk/pg/research/projects/qianzh/sds/",
   "LastModified": "Tue, 12 May 2020 13:16:57 GMT",
   "PageSize": "7383",
   "Keywords": [
    "secur: 21",
    "devic: 21",
    "research: 15",
    "system: 11",
    "smart: 10"
   ],
   "Parents": [
    "https://www.cse.ust.hk/"
   ],
   "Children": [
    "https://www.cse.ust.hk/admin/contact/",
    "https://www.cse.ust.hk/pg/admissions/recruiting/",
    "https://www.cse.ust.hk/admin/search/",
    "https://www.cse.ust.hk/",
    "https://www.cse.ust.hk/pg/",
    "https://www.cse.ust.hk/admin/recruitment/",
    "https://www.cse.ust.hk/ug/enrichment/",
    "https://www.cse.ust.hk/admin/welcome/",
    "https://www.cse.ust.hk/admin/qa/",
    "https://www.cse.ust.hk/pg/ourgraduates/",
    "https://www.cse.ust.hk/ug/",
    "https://www.cse.ust.hk/admin/people/staff/",
    "https://www.cse.ust.hk/admin/facilities/",
    "https://www.cse.ust.hk/Restricted/",
    "https://www.cse.ust.hk/admin/industry_collaboration/",
    "https://www.cse.ust.hk/pg/research/areas/",
    "https://www.cse.ust.hk/pg/research/labs/",
    "https://www.cse.ust.hk/admin/people/faculty/profile/qianzh",
    "https://www.cse.ust.hk/admin/people/alumni/",
    "https://www.cse.ust.hk/admin/about/",
    "https://www.cse.ust.hk/admin/factsheet/",
    "https://www.cse.ust.hk/admin/people/pg/",
    "https://www.cse.ust.hk/pg/research/projects/",
    "https://www.cse.ust.hk/ug/admissions/",
    "https://www.cse.ust.hk/pg/admissions/",
    "https://www.cse.ust.hk/admin/sitemap/",
    "https://www.cse.ust.hk/admin/intranet/",
    "https://www.cse.ust.hk/admin/mission/",
    "https://www.cse.ust.hk/News/",
    "https://www.cse.ust.hk/admin/people/faculty/"
   ]
  },
  {
   "Id": 11,
   "Score": 0.15265625000000002,
   "Title": "CSE Intranet | HKUST CSE",
   "Url": "https://www.cse.ust.hk/admin/intranet/",
   "LastModified": "Tue, 12 May 2020 13:16:57 GMT",
   "PageSize": "1457",
   "Keywords": [
    "research: 8",
    "postgradu: 7",
    "intranet: 5",
    "faculti: 5",
    "cse: 5"
   ],
   "Parents": [
    "https://www.cse.ust.hk/"
   ],
   "Children": [
    "https://www.cse.ust.hk/admin/contact/",
    "https://www.cse.ust.hk/admin/people/faculty/",
    "https://www.cse.ust.hk/admin/qa/",
    "https://www.cse.ust.hk/ug/",
    "https://www.cse.ust.hk/admin/people/alumni/",
    "https://www.cse.ust.hk/admin/industry_collaboration/",
    "https://www.cse.ust.hk/pg/research/areas/",
    "https://www.cse.ust.hk/admin/facilities/committee/",
    "https://www.cse.ust.hk/admin/intranet/",
    "https://www.cse.ust.hk/admin/people/pg/",
    "https://www.cse.ust.hk/ug/enrichment/",
    "https://www.cse.ust.hk/pg/admissions/recruiting/",
    "https://www.cse.ust.hk/ug/hkust_only/",
    "https://www.cse.ust.hk/admin/sitemap/",
    "https://www.cse.ust.hk/pg/",
    "https://www.cse.ust.hk/admin/mission/",
    "https://www.cse.ust.hk/admin/people/staff/",
    "https://www.cse.ust.hk/pg/research/projects/",
    "https://www.cse.ust.hk/pg/admissions/",
    "https://www.cse.ust.hk/pg/hkust_only/",
    "https://www.cse.ust.hk/admin/search/",
    "https://www.cse.ust.hk/News/",
    "https://www.cse.ust.hk/admin/facilities/",
    "https://www.cse.ust.hk/admin/factsheet/",
    "https://www.cse.ust.hk/admin/recruitment/",
    "https://www.cse.ust.hk/admin/about/",
    "https://www.cse.ust.hk/ug/admissions/",
    "https://www.cse.ust.hk/",
    "https://www.cse.ust.hk/admin/welcome/",
    "https://www.cse.ust.hk/pg/research/labs/",
    "https://www.cse.ust.hk/pg/ourgraduates/",
    "https://www.cse.ust.hk/Restricted/"
   ]
  },
  {
   "Id": 9,
   "Score": 0.15265625000000002,
   "Title": "Welcome from Head of Department | HKUST CSE",
   "Url": "https://www.cse.ust.hk/admin/welcome/",
   "LastModified": "Tue, 12 May 2020 13:16:57 GMT",
   "PageSize": "2546",
   "Keywords": [
    "research: 10",
    "depart: 10",
    "postgradu: 8",
    "comput: 8",
    "scienc: 7"
   ],
   "Parents": [
    "https://www.cse.ust.hk/"
   ],
   "Children": [
    "https://www.cse.ust.hk/admin/people/pg/",
    "https://www.cse.ust.hk/pg/ourgraduates/",
    "https://www.cse.ust.hk/ug/",
    "https://www.cse.ust.hk/Restricted/",
    "https://www.cse.ust.hk/admin/people/faculty/",
    "https://www.cse.ust.hk/admin/contact/",
    "https://www.cse.ust.hk/pg/research/areas/",
    "https://www.cse.ust.hk/admin/qa/",
    "https://www.cse.ust.hk/admin/sitemap/",
    "https://www.cse.ust.hk/pg/",
    "https://www.cse.ust.hk/admin/people/alumni/",
    "https://www.cse.ust.hk/admin/mission/",
    "https://www.cse.ust.hk/ug/enrichment/",
    "https://www.cse.ust.hk/admin/search/",
    "https://www.cse.ust.hk/admin/industry_collaboration/",
    "https://www.cse.ust.hk/admin/facilities/",
    "https://www.cse.ust.hk/News/",
    "https://www.cse.ust.hk/ug/admissions/",
    "https://www.cse.ust.hk/admin/people/faculty/profile/dyyeung",
    "https://www.cse.ust.hk/admin/welcome/",
    "https://www.cse.ust.hk/pg/admissions/",
    "https://www.cse.ust.hk/admin/about/",
    "https://www.cse.ust.hk/admin/people/staff/",
    "https://www.cse.ust.hk/admin/recruitment/",
    "https://www.cse.ust.hk/pg/research/labs/",
    "https://www.cse.ust.hk/pg/admissions/recruiting/",
    "https://www.cse.ust.hk/pg/research/projects/",
    "https://www.cse.ust.hk/admin/intranet/",
    "https://www.cse.ust.hk/",
    "https://www.cse.ust.hk/admin/factsheet/"
   ]
  },
  {
   "Id": 18,
   "Score": 0.15265625000000002,
   "Title": "About CSE | HKUST CSE",
   "Url": "https://www.cse.ust.hk/admin/about/",
   "LastModified": "Tue, 12 May 2020 13:16:57 GMT",
   "PageSize": "3137",
   "Keywords": [
    "comput: 19",
    "research: 10",
    "scienc: 9",
    "technolog: 8",
    "postgradu: 7"
   ],
   "Parents": [
    "https://www.cse.ust.hk/"
   ],
   "Children": [
    "https://www.cse.ust.hk/pg/",
    "https://www.cse.ust.hk/admin/mission/",
    "https://www.cse.ust.hk/News/",
    "https://www.cse.ust.hk/ug/enrichment/",
    "https://www.cse.ust.hk/pg/admissions/",
    "https://www.cse.ust.hk/ug/",
    "https://www.cse.ust.hk/Restricted/",
    "https://www.cse.ust.hk/admin/welcome/",
    "https://www.cse.ust.hk/admin/people/staff/",
    "https://www.cse.ust.hk/admin/recruitment/",
    "https://www.cse.ust.hk/pg/research/areas/",
    "https://www.cse.ust.hk/pg/admissions/recruiting/",
    "https://www.cse.ust.hk/admin/intranet/",
    "https://www.cse.ust.hk/admin/search/",
    "https://www.cse.ust.hk/admin/industry_collaboration/",
    "https://www.cse.ust.hk/admin/contact/",
    "https://www.cse.ust.hk/",
    "https://www.cse.ust.hk/admin/factsheet/",
    "https://www.cse.ust.hk/admin/qa/",
    "https://www.cse.ust.hk/ug/admissions/",
    "https://www.cse.ust.hk/admin/about/",
    "https://www.cse.ust.hk/admin/facilities/",
    "https://www.cse.ust.hk/admin/people/alumni/",
    "https://www.cse.ust.hk/pg/research/labs/",
    "https://www.cse.ust.hk/pg/ourgraduates/",
    "https://www.cse.ust.hk/admin/people/faculty/",
    "https://www.cse.ust.hk/admin/people/pg/",
    "https://www.cse.ust.hk/pg/research/projects/",
    "https://www.cse.ust.hk/admin/sitemap/"
   ]
  },
  {
   "Id": 1,
   "Score": 0.15265625000000002,
   "Title": "Research Labs \u0026 Centers | HKUST CSE",
   "Url": "https://www.cse.ust.hk/pg/research/labs/",
   "LastModified": "Tue, 12 May 2020 13:16:57 GMT",
   "PageSize": "1562",
   "Keywords": [
    "research: 10",
    "lab: 7",
    "postgradu: 7",
    "undergradu: 5",
    "center: 4"
   ],
   "Parents": [
    "https://www.cse.ust.hk/"
   ],
   "Children": [
    "https://www.cse.ust.hk/admin/contact/",
    "https://www.cse.ust.hk/admin/people/staff/",
    "https://www.cse.ust.hk/admin/qa/",
    "https://www.cse.ust.hk/pg/admissions/",
    "https://www.cse.ust.hk/pg/ourgraduates/",
    "https://www.cse.ust.hk/stc/",
    "https://www.cse.ust.hk/",
    "https://www.cse.ust.hk/admin/welcome/",
    "https://www.cse.ust.hk/admin/people/pg/",
    "https://www.cse.ust.hk/admin/intranet/",
    "https://www.cse.ust.hk/pg/",
    "https://www.cse.ust.hk/admin/people/alumni/",
    "https://www.cse.ust.hk/admin/industry_collaboration/",
    "https://www.cse.ust.hk/pg/research/projects/",
    "https://www.cse.ust.hk/admin/sitemap/",
    "https://www.cse.ust.hk/admin/recruitment/",
    "https://www.cse.ust.hk/admin/about/",
    "https://www.cse.ust.hk/pg/research/labs/",
    "https://www.cse.ust.hk/admin/facilities/",
    "https://www.cse.ust.hk/BDI/WHATLab/",
    "https://www.cse.ust.hk/admin/search/",
    "https://www.cse.ust.hk/ug/",
    "https://www.cse.ust.hk/Restricted/",
    "https://www.cse.ust.hk/admin/mission/",
    "https://www.cse.ust.hk/pg/research/areas/",
    "https://www.cse.ust.hk/ug/admissions/",
    "https://www.cse.ust.hk/~hltc/",
    "https://www.cse.ust.hk/News/",
    "https://www.cse.ust.hk/ug/enrichment/",
    "https://www.cse.ust.hk/admin/factsheet/",
    "https://www.cse.ust.hk/admin/people/faculty/",
    "https://www.cse.ust.hk/pg/admissions/recruiting/"
   ]
  },
  {
   "Id": 19,
   "Score": 0.15265625000000002,
   "Title": "Computing Facilities | HKUST CSE",
   "Url": "https://www.cse.ust.hk/admin/facilities/",
   "LastModified": "Tue, 12 May 2020 13:16:57 GMT",
   "PageSize": "2876",
   "Keywords": [
    "research: 15",
    "lab: 14",
    "comput: 9",
    "postgradu: 7",
    "depart: 6"
   ],
   "Parents": [
    "https://www.cse.ust.hk/"
   ],
   "Children": [
    "https://www.cse.ust.hk/",
    "https://www.cse.ust.hk/pg/",
    "https://www.cse.ust.hk/ug/",
    "https://www.cse.ust.hk/admin/industry_collaboration/",
    "https://www.cse.ust.hk/admin/people/pg/",
    "https://www.cse.ust.hk/ug/enrichment/",
    "https://www.cse.ust.hk/pg/ourgraduates/",
    "https://www.cse.ust.hk/admin/facilities/committee/",
    "https://www.cse.ust.hk/admin/people/alumni/",
    "https://www.cse.ust.hk/admin/recruitment/",
    "https://www.cse.ust.hk/admin/welcome/",
    "https://www.cse.ust.hk/admin/people/staff/",
    "https://www.cse.ust.hk/pg/admissions/recruiting/",
    "https://www.cse.ust.hk/admin/intranet/",
    "https://www.cse.ust.hk/Restricted/",
    "https://www.cse.ust.hk/pg/research/projects/",
    "https://www.cse.ust.hk/admin/about/",
    "https://www.cse.ust.hk/pg/research/areas/",
    "https://www.cse.ust.hk/pg/admissions/",
    "https://www.cse.ust.hk/admin/mission/",
    "https://www.cse.ust.hk/admin/factsheet/",
    "https://www.cse.ust.hk/admin/qa/",
    "https://www.cse.ust.hk/admin/search/",
    "https://www.cse.ust.hk/pg/research/labs/",
    "https://www.cse.ust.hk/admin/sitemap/",
    "https://www.cse.ust.hk/News/",
    "https://www.cse.ust.hk/admin/contact/",
    "https://www.cse.ust.hk/admin/people/faculty/",
    "https://www.cse.ust.hk/admin/facilities/",
    "https://www.cse.ust.hk/ug/admissions/"
   ]
  },
  {
   "Id": 8,
   "Score": 0.15000000000000002,
   "Title": "Department of Computer Science and Engineering - HKUST",
   "Url": "https://www.cse.ust.hk/",
   "LastModified": "Tue, 12 May 2020 13:16:56 GMT",
   "PageSize": "4597",
   "Keywords": [
    "research: 16",
    "2020: 12",
    "learn: 10",
    "forum: 10",
    "alumni: 10"
   ],
   "Parents": null,
   "Children": [
    "https://www.cse.ust.hk/pg/research/projects/qianzh/sds/",
    "https://www.cse.ust.hk/admin/intranet/",
    "https://www.cse.ust.hk/admin/welcome/",
    "https://www.cse.ust.hk/admin/about/",
    "https://www.cse.ust.hk/pg/research/labs/",
    "https://www.cse.ust.hk/admin/facilities/",
    "https://www.cse.ust.hk/ug/enrichment/",
    "https://www.cse.ust.hk/pg/research/projects/yqsong/robo-lawyer/",
    "https://www.cse.ust.hk/Restricted/",
    "https://www.cse.ust.hk/pg/research/projects/leichen/stc/",
    "https://www.cse.ust.hk/pg/research/projects/mxj/hri/",
    "https://www.cse.ust.hk/pg/research/projects/yike/aqp/",
    "https://www.cse.ust.hk/pg/research/projects/gchan/lst/",
    "https://www.cse.ust.hk/admin/industry_collaboration/",
    "https://www.cse.ust.hk/admin/people/staff/",
    "https://www.cse.ust.hk/pg/research/areas/",
    "https://www.cse.ust.hk/ug/admissions/",
    "https://www.cse.ust.hk/pg/admissions/",
    "https://www.cse.ust.hk/pg/admissions/recruiting/",
    "https://www.cse.ust.hk/event/RIAF2020/",
    "https://www.cse.ust.hk/admin/search/",
    "https://www.cse.ust.hk/News/",
    "https://www.cse.ust.hk/admin/contact/",
    "https://www.cse.ust.hk/admin/people/faculty/",
    "https://www.cse.ust.hk/pg/research/projects/dyyeung/ml-hko/",
    "https://www.cse.ust.hk/pg/research/projects/horner/mmm/",
    "https://www.cse.ust.hk/admin/recruitment/",
    "https://www.cse.ust.hk/admin/mission/",
    "https://www.cse.ust.hk/admin/qa/",
    "https://www.cse.ust.hk/event/RTF2020/",
    "https://www.cse.ust.hk/pg/research/projects/kaichen/coda/",
    "https://www.cse.ust.hk/pg/research/projects/scc/castle/",
    "https://www.cse.ust.hk/ug/",
    "https://www.cse.ust.hk/admin/people/alumni/",
    "https://www.cse.ust.hk/pg/ourgraduates/",
    "https://www.cse.ust.hk/pg/research/projects/raywong/findyourfavorite/",
    "https://www.cse.ust.hk/pg/research/projects/charlesz/pinpoint/",
    "https://www.cse.ust.hk/",
    "https://www.cse.ust.hk/pg/",
    "https://www.cse.ust.hk/admin/factsheet/",
    "https://www.cse.ust.hk/admin/people/pg/",
    "https://www.cse.ust.hk/pg/research/projects/",
    "https://www.cse.ust.hk/pg/research/projects/dyyeung/ml-ed/",
    "https://www.cse.ust.hk/event/BDICareerFair2020/",
    "https://www.cse.ust.hk/News/events.html",
    "https://www.cse.ust.hk/pg/research/projects/lzhang/aipano/",
    "https://www.cse.ust.hk/pg/research/projects/cqf/lsi/",
    "https://www.cse.ust.hk/admin/sitemap/"
   ]
  }
 ]
}